taggedunion/__init__.py
taggedunion-0.0.2.dist-info/LICENSE
taggedunion-0.0.2.dist-info/METADATA
taggedunion-0.0.2.dist-info/WHEEL
taggedunion-0.0.2.dist-info/top_level.txt
taggedunion-0.0.2.dist-info/RECORD
